src/__init__.py
src/cli.py
mectl-0.1.1.dist-info/METADATA
mectl-0.1.1.dist-info/WHEEL
mectl-0.1.1.dist-info/entry_points.txt
mectl-0.1.1.dist-info/RECORD
